wingcommander/commander.py
wingcommander/__init__.py
wingcommander/test.py
wingcommander/util/__init__.py
wingcommander/util/completion.py
wingcommander/util/tablize.py
wingcommander-0.1.5.dist-info/WHEEL
wingcommander-0.1.5.dist-info/top_level.txt
wingcommander-0.1.5.dist-info/metadata.json
wingcommander-0.1.5.dist-info/METADATA
wingcommander-0.1.5.dist-info/RECORD
wingcommander-0.1.5.dist-info/DESCRIPTION.rst
