Metadata-Version: 2.0
Name: wingcommander
Version: 0.1.5
Summary: Pythonic commandline applications
Home-page: http://jdost.us/wingcommander/
Author: Jeff Ostendorf
Author-email: jostendorf@gmail.com
License: Apache 2.0
Platform: UNKNOWN
Classifier: Development Status :: 3 - Alpha
Classifier: Intended Audience :: Developers
Classifier: Natural Language :: English
Classifier: License :: OSI Approved :: Apache Software License
Classifier: Operating System :: Unix
Classifier: Operating System :: MacOS
Classifier: Environment :: Console
Classifier: Programming Language :: Python
Classifier: Programming Language :: Python :: 2.7
